[
    {
        "id": "1",
        "company": "Facebook",
        "country": "India",
        "city": "Bangalore",
        "skills": "Mobile App developer",
        "jobType": "",
        "type1": "full",
        "type2": "remote",
        "type3": "senior",
        "postedOn": "1 day ago",
        "bookmarked": false,
        "byWhom": "affiidy",
        "image": ""
    },
        {
        "id": "2",
        "company": "Instagram",
        "country": "India",
        "city": "Chennai",
        "skills": "Mobile App developer",
        "jobType": "",
        "type1": "full",
        "type2": "remote",
        "type3": "senior",
        "postedOn": "7 day ago",
        "bookmarked": false,
        "byWhom": "affiidy",
        "image": ""
    },
        {
        "id": "3",
        "company": "Google",
        "country": "India",
        "city": "Pune",
        "skills": "Mobile App developer",
        "jobType": "",
        "type1": "full",
        "type2": "remote",
        "type3": "senior",
        "postedOn": "10 day ago",
        "bookmarked": false,
        "byWhom": "affiidy",
        "image": ""
    },
        {
        "id": "4",
        "company": "Microsoft",
        "country": "India",
        "city": "Mumbai",
        "skills": "Mobile App developer",
        "jobType": "",
        "type1": "full",
        "type2": "remote",
        "type3": "senior",
        "postedOn": "30 day ago",
        "bookmarked": false,
        "byWhom": "affiidy",
        "image": ""
    },
        {
        "id": "5",
        "company": "Messenger",
        "country": "India",
        "city": "Delhi",
        "skills": "Mobile App developer",
        "jobType": "",
        "type1": "full",
        "type2": "remote",
        "type3": "senior",
        "postedOn": "4 day ago",
        "bookmarked": false,
        "byWhom": "affiidy",
        "image": ""
    },
        {
        "id": "6",
        "company": "JP Morgan",
        "country": "India",
        "city": "Bangalore",
        "skills": "Mobile App developer",
        "jobType": "",
        "type1": "full",
        "type2": "remote",
        "type3": "senior",
        "postedOn": "16 day ago",
        "bookmarked": true,
        "byWhom": "affiidy",
        "image": ""
    },
        {
        "id": "7",
        "company": "Facebook",
        "country": "India",
        "city": "Bangalore",
        "skills": "Mobile App developer",
        "jobType": "",
        "type1": "full",
        "type2": "remote",
        "type3": "senior",
        "postedOn": "1 day ago",
        "bookmarked": false,
        "byWhom": "affiidy",
        "image": ""
    }
]